stadion/__init__.py
stadion/_version.py
stadion/data.py
stadion/inference.py
stadion/kds.py
stadion/parameters.py
stadion/sde.py
stadion/utils.py
stadion/models/__init__.py
stadion/models/linear.py
stadion/models/mlp.py
stadion-1.0.2.dist-info/LICENCE
stadion-1.0.2.dist-info/METADATA
stadion-1.0.2.dist-info/WHEEL
stadion-1.0.2.dist-info/top_level.txt
stadion-1.0.2.dist-info/RECORD
