Metadata-Version: 2.2
Name: stadion
Version: 1.0.2
Summary: Causal Modeling with Stationary Diffusions
Home-page: https://github.com/larslorch/stadion
Author: Lars Lorch
Author-email: lars.lorch@inf.ethz.ch
Classifier: Programming Language :: Python :: 3
Classifier: License :: OSI Approved :: MIT License
Classifier: Operating System :: OS Independent
License-File: LICENCE
Requires-Dist: jax>=0.4.0
Requires-Dist: jaxlib>=0.4.0
Requires-Dist: optax>=0.1.3
Requires-Dist: tensorflow>=2.9.0
Requires-Dist: tensorflow_datasets>=4.3.0
Requires-Dist: numpy>=1.19.0
Dynamic: author
Dynamic: author-email
Dynamic: classifier
Dynamic: home-page
Dynamic: requires-dist
Dynamic: summary
